{
  "--OS_StatusBar": "rgba(0,0,0,1)",
  "--OSHomeIndicator": "rgba(0,0,0,1)",
  "--OS_LightMode": 0,
  "--OS_DarkMode": 0,
  "--OS_ModalStackStatusBariOSBackground": "rgba(0,0,0,1)",
  "--OS_AppleKeyboardKeyboardbackground": "rgba(206,208,213,1)",
  "--OS_ModalStackStatusBarAndroidBackground": "rgba(255,255,255,1)",
  "--OS_AppleKeyboardKeyBackground": "rgba(252,252,254,1)",
  "--OS_AppleKeyboardKeyBackgroundAlt01": "rgba(171,176,186,1)",
  "--OS_AppleKeyboardKeyBackgroundShadow": "rgba(131,133,138,1)",
  "--OS_AppleKeyboardKeyText": "rgba(0,0,0,1)",
  "--OS_AppleKeyboardIcon": "rgba(89,90,96,1)",
  "--OS_ModalStackStatusBariOS": "rgba(255,255,255,1)",
  "--OS_ModalStackStatusBarAndroid": "rgba(0,0,0,1)",
  "--OSHittargetareaDefault": 48,
  "--TypesStyle0FontFamily": "GT-Ultra Median",
  "--TypesStyle0FontWeight": "Black",
  "--TypesStyle0FontSize": 40,
  "--TypesStyle0LineHeight": 44,
  "--TypesStyle0LineSpacing": 44,
  "--TypesStyle0LetterSpacing": 0,
  "--TypesStyle0iOSClassification": "Large-Title",
  "--TypesStyle1FontFamily": "GT-Ultra Median",
  "--TypesStyle1FontWeight": "Bold",
  "--TypesStyle1FontSize": 29,
  "--TypesStyle1LineHeight": 32,
  "--TypesStyle1LineSpacing": 32,
  "--CornerRadiusNone": 0,
  "--SpacingNone": 0,
  "--BackgroundPageDefault": "rgba(241,241,241,1)",
  "--BackgroundPage_DefaultAlt01": "rgba(241,241,241,1)",
  "--BackgroundSectionDefault": "rgba(241,241,241,1)",
  "--BackgroundPanelDefault": "rgba(255,255,255,1)",
  "--BackgroundPanelSecondary": "rgba(241,241,241,1)",
  "--BackgroundPanelPressed": "rgba(201,201,201,1)",
  "--BackgroundPanelTransparent": "rgba(0,0,0,0)",
  "--BackgroundSectionDefaultAlt01": "rgba(255,255,255,1)",
  "--BackgroundSectionBrand": "rgba(241,241,241,1)",
  "--BackgroundSectionBrandAlt01": "rgba(241,241,241,1)",
  "--BackgroundActionDefault": "rgba(0,0,0,1)",
  "--BackgroundActionDefaultAlt01": "rgba(0,0,0,0)",
  "--BackgroundActionPressed": "rgba(50,50,51,1)",
  "--BackgroundActionDisabled": "rgba(201,201,201,1)",
  "--BackgroundSentimentCritical": "rgba(255,246,245,1)",
  "--BackgroundActionOnColorDefault": "rgba(255,255,255,1)",
  "--BackgroundActionOnColorDefaultAlt01": "rgba(0,0,0,0)",
  "--BackgroundActionOnColorPressed": "rgba(50,50,51,1)",
  "--BackgroundActionOnColorDisabled": "rgba(201,201,201,1)",
  "--BackgroundSentimentCriticalAlt01": "rgba(255,246,245,1)",
  "--BackgroundSentimentCriticalAlt02": "rgba(219,15,48,1)",
  "--BackgroundSentimentWarning": "rgba(255,247,232,1)",
  "--BackgroundSentimentWarningAlt01": "rgba(255,247,232,1)",
  "--BackgroundSentimentSuccess": "rgba(246,249,245,1)",
  "--BackgroundSentimentSuccessAlt01": "rgba(246,249,245,1)",
  "--BackgroundSentimentInfo": "rgba(248,248,255,1)",
  "--BackgroundSentimentInfoAlt01": "rgba(248,248,255,1)",
  "--BackgroundInputDefault": "rgba(255,255,255,1)",
  "--BackgroundInputDisabled": "rgba(241,241,241,1)",
  "--BorderWidthNone": 0,
  "--BorderWidth01": 1,
  "--BorderWidth02": 2,
  "--BackgroundOverlayDefault": "rgba(0,0,0,0.65)",
  "--BackgroundOverlayDefaultAlt01": "rgba(0,0,0,0.65)",
  "--SpacingSize04": 4,
  "--SpacingSize08": 8,
  "--SpacingSize12": 12,
  "--SpacingSize16": 16,
  "--SpacingSize24": 24,
  "--SpacingSize32": 32,
  "--SpacingSize48": 48,
  "--CornerRadiusSmall": 8,
  "--CornerRadiusDefault": 12,
  "--CornerRadiusMedium": 16,
  "--CornerRadiusFull": 200,
  "--CornerRadiusCircle": 9999,
  "--TextGenericDefault": "rgba(0,0,0,1)",
  "--TextGenericDefaultAlt01": "rgba(255,255,255,1)",
  "--TextGenericSubdued": "rgba(118,118,118,1)",
  "--TextGenericBrand": "rgba(0,0,0,1)",
  "--TextGenericBrandAlt01": "rgba(0,0,0,1)",
  "--TextGenericBrandAlt02": "rgba(0,0,0,1)",
  "--TextGenericBrandAlt03": "rgba(0,0,0,1)",
  "--IconGenericDefault": "rgba(0,0,0,1)",
  "--IconGenericDefaultAlt01": "rgba(255,255,255,1)",
  "--IconGenericSubdued": "rgba(118,118,118,1)",
  "--IconGenericSubduedAlt01": "rgba(118,118,118,1)",
  "--IconGenericBrand": "rgba(0,0,0,1)",
  "--IconGenericBrandAlt01": "rgba(0,0,0,1)",
  "--IconGenericBrandAlt02": "rgba(0,0,0,1)",
  "--IconGenericBrandAlt03": "rgba(0,0,0,1)",
  "--TextActionDefault": "rgba(0,0,0,1)",
  "--TextActionDefaultAlt01": "rgba(255,255,255,1)",
  "--TextActionInverse": "rgba(0,0,0,1)",
  "--TextActionInverseAlt01": "rgba(255,255,255,1)",
  "--TextActionPressed": "rgba(0,0,0,1)",
  "--TextActionPressedAlt01": "rgba(255,255,255,1)",
  "--TextActionDisabled": "rgba(118,118,118,1)",
  "--TextSentimentCritical": "rgba(0,0,0,1)",
  "--TextSentimentCriticalAlt01": "rgba(255,255,255,1)",
  "--TextSentimentCriticalAlt02": "rgba(219,15,48,1)",
  "--TextSentimentWarning": "rgba(0,0,0,1)",
  "--TextSentimentSuccess": "rgba(0,0,0,1)",
  "--TextSentimentInfo": "rgba(0,0,0,1)",
  "--TextInputLabel": "rgba(0,0,0,1)",
  "--TextInputPlaceholder": "rgba(118,118,118,1)",
  "--TextInputDefault": "rgba(0,0,0,1)",
  "--TextInputDefaultAlt01": "rgba(0,0,0,1)",
  "--TextInputDisabled": "rgba(118,118,118,1)",
  "--TextInputError": "rgba(223,21,54,1)",
  "--TextInputValidated": "rgba(12,135,28,1)",
  "--IconActionDefault": "rgba(0,0,0,1)",
  "--IconSentimentCritical": "rgba(219,15,48,1)",
  "--IconSentimentCriticalAlt01": "rgba(255,255,255,1)",
  "--IconSentimentWarning": "rgba(224,105,0,1)",
  "--IconSentimentSuccess": "rgba(15,159,106,1)",
  "--IconSentimentInfo": "rgba(39,106,230,1)",
  "--ComponentPromoBackgroundDefault": "rgba(255,255,255,1)",
  "--ComponentPromoBackgroundPrimary": "rgba(17,182,122,1)",
  "--ComponentPromoBackgroundPrimaryAlt01": "rgba(0,106,77,1)",
  "--ComponentPromoBackgroundPrimaryAlt02": "rgba(2,71,49,1)",
  "--ComponentPromoBackgroundPrimaryAlt03": "rgba(108,244,121,1)",
  "--ComponentPromoBackgroundSecondary": "rgba(199,255,198,1)",
  "--ComponentPromoBackgroundSecondaryAlt01": "rgba(161,159,255,1)",
  "--ComponentPromoBackgroundSecondaryAlt02": "rgba(245,178,242,1)",
  "--ComponentPromoBackgroundSecondaryAlt03": "rgba(157,231,222,1)",
  "--ComponentPromoBackgroundSecondaryAlt04": "rgba(255,177,106,1)",
  "--ComponentPromoTextDefault": "rgba(0,0,0,1)",
  "--ComponentPromoTextPrimary": "rgba(0,0,0,1)",
  "--ComponentPromoTextPrimaryAlt01": "rgba(255,255,255,1)",
  "--ComponentPromoTextPrimaryAlt02": "rgba(255,255,255,1)",
  "--ComponentPromoTextPrimaryAlt03": "rgba(0,0,0,1)",
  "--ComponentPromoTextSecondary": "rgba(0,0,0,1)",
  "--ComponentPromoTextSecondaryAlt01": "rgba(0,0,0,1)",
  "--ComponentPromoTextSecondaryAlt02": "rgba(0,0,0,1)",
  "--ComponentPromoTextSecondaryAlt03": "rgba(0,0,0,1)",
  "--ComponentPromoTextSecondaryAlt04": "rgba(0,0,0,1)",
  "--ComponentPromoIconGenricDefault": "rgba(0,0,0,1)",
  "--ComponentPromoIconGenricPrimary": "rgba(0,0,0,1)",
  "--ComponentPromoIconGenricPrimaryAlt01": "rgba(255,255,255,1)",
  "--ComponentPromoIconGenricPrimaryAlt02": "rgba(255,255,255,1)",
  "--ComponentPromoIconGenricPrimaryAlt03": "rgba(0,0,0,1)",
  "--ComponentPromoIconGenricSecondary": "rgba(0,0,0,1)",
  "--ComponentPromoIconGenricSecondaryAlt01": "rgba(0,0,0,1)",
  "--ComponentPromoIconGenricSecondaryAlt02": "rgba(0,0,0,1)",
  "--ComponentPromoIconGenricSecondaryAlt03": "rgba(0,0,0,1)",
  "--ComponentPromoIconGenricSecondaryAlt04": "rgba(0,0,0,1)",
  "--ComponentPromoIconCanvasDefault": "rgba(255,255,255,1)",
  "--ComponentPromoIconCanvasPrimary": "rgba(17,182,122,1)",
  "--ComponentPromoIconCanvasPrimaryAlt01": "rgba(0,106,77,1)",
  "--ComponentPromoIconCanvasPrimaryAlt02": "rgba(2,71,49,1)",
  "--ComponentPromoIconCanvasPrimaryAlt03": "rgba(108,244,121,1)",
  "--ComponentPromoIconCanvasSecondary": "rgba(199,255,198,1)",
  "--ComponentPromoIconCanvasSecondaryAlt01": "rgba(161,159,255,1)",
  "--ComponentPromoIconCanvasSecondaryAlt02": "rgba(245,178,242,1)",
  "--ComponentPromoIconCanvasSecondaryAlt03": "rgba(157,231,222,1)",
  "--ComponentPromoIconCanvasSecondaryAlt04": "rgba(255,177,106,1)",
  "--ComponentActionButtonDefaultCornerRadius": 12,
  "--ComponentActionButtonBorderWidth": 1,
  "--ComponentCompactButtonDefaultCornerRadius": 12,
  "--ComponentCompactButtonSmallCornerRadius": 8,
  "--ComponentCompactButtonBorderWidth": 1,
  "--ComponentCompactButtonSmallMinHeight": 36,
  "--ComponentIconButtonDefaultCornerRadius": 9999,
  "--ComponentIconButtonBorderWidth": 1,
  "--ComponentIconButtonSmallMinSize": 32,
  "--ComponentBrandAccentButtonDefaultCornerRadius": 12,
  "--ComponentCarouselIndicatorItemActive": "rgba(0,0,0,1)",
  "--ComponentCarouselIndicatorItemInactive": "rgba(118,118,118,1)",
  "--ComponentCarouselIndicatorOnColorItemActive": "rgba(0,0,0,1)",
  "--ComponentCarouselIndicatorOnColorItemInactive": "rgba(118,118,118,1)",
  "--ComponentBrandAccentButtonPrimaryBackgroundDefault": "rgba(11,226,72,1)",
  "--ComponentBrandAccentButtonPrimaryBackgroundPressed": "rgba(108,244,121,1)",
  "--ComponentBrandAccentButtonPrimaryBorderDefault": "rgba(11,226,72,1)",
  "--ComponentBrandAccentButtonPrimaryBorderPressed": "rgba(108,244,121,1)",
  "--ComponentBrandAccentButtonPrimaryTextDefault": "rgba(0,0,0,1)",
  "--ComponentBrandAccentButtonPrimaryTextPressed": "rgba(0,0,0,1)",
  "--ComponentBrandAccentButtonPrimaryIconDefault": "rgba(0,0,0,1)",
  "--ComponentBrandAccentButtonPrimaryIconPressed": "rgba(0,0,0,1)",
  "--ComponentPictogramIconDefault": "rgba(0,0,0,1)",
  "--ComponentPictogramIconDefaultAlt01": "rgba(0,0,0,1)",
  "--ComponentPictogramIconPrimary": "rgba(0,0,0,1)",
  "--ComponentPictogramIconPrimaryAlt01": "rgba(255,255,255,1)",
  "--ComponentPictogramIconPrimaryAlt02": "rgba(255,255,255,1)",
  "--ComponentPictogramIconPrimaryAlt03": "rgba(0,0,0,1)",
  "--ComponentPictogramIconSecondary": "rgba(0,0,0,1)",
  "--ComponentPictogramIconSecondaryAlt01": "rgba(0,0,0,1)",
  "--ComponentPictogramIconSecondaryAlt02": "rgba(0,0,0,1)",
  "--ComponentPictogramIconSecondaryAlt03": "rgba(0,0,0,1)",
  "--ComponentPictogramIconSecondaryAlt04": "rgba(0,0,0,1)",
  "--ComponentPictogramIconCanvasDefault": "rgba(199,255,198,1)",
  "--ComponentPictogramIconCanvasDefaultAlt01": "rgba(0,0,0,0)",
  "--ComponentPictogramIconCanvasDefaultAlt02": "rgba(241,241,241,1)",
  "--ComponentPictogramIconCanvasPrimary": "rgba(17,182,122,1)",
  "--ComponentPictogramIconCanvasPrimaryAlt01": "rgba(0,106,77,1)",
  "--ComponentPictogramIconCanvasPrimaryAlt02": "rgba(2,71,49,1)",
  "--ComponentPictogramIconCanvasPrimaryAlt03": "rgba(108,244,121,1)",
  "--ComponentPictogramIconCanvasSecondary": "rgba(199,255,198,1)",
  "--ComponentPictogramIconCanvasSecondaryAlt01": "rgba(161,159,255,1)",
  "--ComponentPictogramIconCanvasSecondaryAlt02": "rgba(245,178,242,1)",
  "--ComponentPictogramIconCanvasSecondaryAlt03": "rgba(157,231,222,1)",
  "--ComponentPictogramIconCanvasSecondaryAlt04": "rgba(255,177,106,1)",
  "--ComponentPictogramIllustrationCanvasDefault": "rgba(199,255,198,1)",
  "--ComponentPictogramIllustrationCanvasDefaultAlt01": "rgba(255,255,255,1)",
  "--ComponentPictogramIllustrationCanvasDefaultAlt02": "rgba(241,241,241,1)",
  "--ComponentPictogramIllustrationCanvasPrimary": "rgba(17,182,122,1)",
  "--ComponentPictogramIllustrationCanvasPrimaryAlt01": "rgba(0,106,77,1)",
  "--ComponentPictogramIllustrationCanvasPrimaryAlt02": "rgba(2,71,49,1)",
  "--ComponentPictogramIllustrationCanvasPrimaryAlt03": "rgba(108,244,121,1)",
  "--ComponentPictogramIllustrationCanvasSecondary": "rgba(199,255,198,1)",
  "--ComponentPictogramIllustrationCanvasSecondaryAlt01": "rgba(161,159,255,1)",
  "--ComponentPictogramIllustrationCanvasSecondaryAlt02": "rgba(245,178,242,1)",
  "--ComponentPictogramIllustrationCanvasSecondaryAlt03": "rgba(157,231,222,1)",
  "--ComponentPictogramIllustrationCanvasSecondaryAlt04": "rgba(255,177,106,1)",
  "--IconActionDefaultAlt01": "rgba(255,255,255,1)",
  "--IconActionPressed": "rgba(0,0,0,1)",
  "--IconActionPressedAlt01": "rgba(255,255,255,1)",
  "--IconActionInverse": "rgba(0,0,0,1)",
  "--IconActionInverseAlt01": "rgba(255,255,255,1)",
  "--IconActionDisabled": "rgba(118,118,118,1)",
  "--IconActionDisabledAlt01": "rgba(0,0,0,0)",
  "--ComponentHeader_LogoBrand": "rgba(0,0,0,1)",
  "--ComponentHeaderDropShadowDefault": "rgba(0,0,0,0.2)",
  "--ComponentHeaderDropShadowBlur": 4,
  "--ComponentHeaderDropShadowXAxis": 0,
  "--ComponentHeaderDropShadowYAxis": 6,
  "--ComponentHeader_LogoBrandAlt01": "rgba(0,106,77,1)",
  "--ComponentIconbuttonCornerradius": 200,
  "--ComponentSelectCategoryItemBackgroundDefault": "rgba(255,255,255,1)",
  "--ComponentSelectCategoryItemBorderDefault": "rgba(201,201,201,1)",
  "--ComponentSelectCategoryItemIconDefault": "rgba(0,0,0,1)",
  "--ComponentSelectCategoryItemBackgroundActive": "rgba(11,226,72,1)",
  "--ComponentSelectCategoryItemBorderActive": "rgba(0,0,0,1)",
  "--ComponentSelectCategoryItemIconActive": "rgba(0,0,0,1)",
  "--ComponentSkeletonShimmer": "rgba(241,241,241,1)",
  "--ComponentInputMinHeight": 56,
  "--ComponentSpinnerSplashScreenStyle01Border": "rgba(0,0,0,1)",
  "--ComponentSpinnerSplashScreenStyle01BorderHighlight": "rgba(11,226,72,1)",
  "--ComponentSpinnerSplashScreenText": "rgba(0,0,0,1)",
  "--ComponentSpinnerSplashScreenStyle01Icon": "rgba(0,0,0,1)",
  "--ComponentTempInputMinHeight": 56,
  "--ComponentStatusBarTimePlusLevels": "rgba(0,0,0,1)",
  "--ComponentTempInputBorderwidthDefault": 1,
  "--ComponentTempInputBorderwidthActive": 2,
  "--ComponentTempInputCornerradius": 12,
  "--ComponentInputCornerRadius": 12,
  "--ComponentTempInputBackgroundHint": "rgba(0,0,0,0)",
  "--ComponentTempInputBackgroundSuccess": "rgba(0,0,0,0)",
  "--ComponentTempInputBackgroundError": "rgba(0,0,0,0)",
  "--ComponentInputCursor": "rgba(0,0,0,1)",
  "--ComponentInputCursorselected": "rgba(0,0,0,1)",
  "--ComponentInputCheckboxTick": "rgba(0,0,0,1)",
  "--ComponentTempInputBorderError": "rgba(0,0,0,0)",
  "--ComponentTempInputBorderUnderline": "rgba(0,0,0,0)",
  "--ComponentTempInputBorderUnderlineActive": "rgba(0,0,0,0)",
  "--ComponentTempInputBorderUnderlineError": "rgba(0,0,0,0)",
  "--ComponentTempInputBorderUnderlineDisabled": "rgba(0,0,0,0)",
  "--ComponentTempInputClearIcon": "rgba(0,0,0,1)",
  "--ComponentTempInputCursor": "rgba(0,0,0,1)",
  "--ComponentTempInputCursorselected": "rgba(0,0,0,1)",
  "--ComponentTempInputLeftLabel": "rgba(0,0,0,1)",
  "--ComponentTempInputRightText": "rgba(0,0,0,1)",
  "--ComponentTempInputTextHint": "rgba(0,0,0,1)",
  "--ComponentTempInputTextHintError": "rgba(223,21,54,1)",
  "--ComponentTempInputTextMasked": "rgba(0,0,0,1)",
  "--ComponentTempInputTextMaskedDisabled": "rgba(118,118,118,1)",
  "--ComponentTempInputIconActionBackground": "rgba(0,0,0,0)",
  "--ComponentTempInputIconAction": "rgba(0,0,0,1)",
  "--ComponentTempInputIconActionAlt01": "rgba(0,0,0,1)",
  "--ComponentTempInputHintmessageCornerradius": 12,
  "--ComponentTempInputHintmessageMarginspacing": 0,
  "--ComponentTempInputHintmessagePaddingSpacing": 0,
  "--ComponentTempInputCheckboxBorderwidth": 1,
  "--ComponentTempInputCheckboxCornerRadius": 8,
  "--ComponentTempInputRadioButtonBorderwidth": 1,
  "--ComponentTempInputMIFieldPasswordInput": "rgba(0,0,0,1)",
  "--ComponentTempInputSortCodeBorderwidthDefault": 1,
  "--ComponentTempInputSortCodeBorderwidthActive": 2,
  "--ComponentTempInputSortCodeValidationmessagespacing": 0,
  "--ComponentTempInputMIFieldShape01CornerRadius": 8,
  "--ComponentTempInputMIFieldShape01": 0,
  "--ComponentTempInputMIFieldShape02": 0,
  "--ComponentTempInputCheckboxBackgroundActive": "rgba(255,255,255,1)",
  "--ComponentTempInputCheckboxBorderActive": "rgba(0,0,0,1)",
  "--ComponentTempInputCheckboxBorderCritical": "rgba(219,15,48,1)",
  "--ComponentTempInputCheckboxTickDefault": "rgba(0,0,0,1)",
  "--ComponentTempInputCheckboxTickActiveDisabled": "rgba(0,0,0,1)",
  "--ComponentTempInputRadioButtonBackgroundActive": "rgba(255,255,255,1)",
  "--ComponentTempInputRadioButtonBorderActive": "rgba(0,0,0,1)",
  "--ComponentTempInputRadioButtonBorderCritical": "rgba(219,15,48,1)",
  "--ComponentTempInputRadioButtonDotDefault": "rgba(0,0,0,1)",
  "--ComponentTempInputRadioButtonDotActiveDisabled": "rgba(0,0,0,1)",
  "--ComponentTempAccordionExpandedPanelBackground": "rgba(255,255,255,1)",
  "--ComponentTempBarChartBackground": "rgba(0,63,46,1)",
  "--ComponentTempBarChartGrid": "rgba(118,118,118,1)",
  "--ComponentTempBarChartDefault": "rgba(119,186,0,1)",
  "--ComponentTempBarChartCurrentAccount": "rgba(0,63,46,1)",
  "--ComponentTempBarChartSavingsAccount": "rgba(100,156,0,1)",
  "--ComponentTempBarChartInvestment": "rgba(153,195,183,1)",
  "--ComponentTempButtonPrimary2Background": "rgba(11,226,72,1)",
  "--ComponentTempButtonPrimary2Backgroundpressed": "rgba(108,250,121,1)",
  "--ComponentTempButtonPrimary2TextDefault": "rgba(0,0,0,1)",
  "--ComponentTempButtonPrimary2TextPressed": "rgba(0,0,0,1)",
  "--ComponentTempButtonPrimary2onColorBackground": "rgba(11,226,72,1)",
  "--ComponentTempButtonPrimary2onColorBackgroundpressed": "rgba(108,250,121,1)",
  "--ComponentTempButtonPrimary2onColorTextDefault": "rgba(0,0,0,1)",
  "--ComponentTempButtonPrimary2onColorTextPressed": "rgba(0,0,0,1)",
  "--ComponentTempButtonPrimary3Background": "rgba(0,0,0,1)",
  "--ComponentTempButtonPrimary3Backgroundpressed": "rgba(50,50,51,1)",
  "--ComponentTempButtonPrimary3TextDefault": "rgba(255,255,255,1)",
  "--ComponentTempButtonPrimary3TextPressed": "rgba(255,255,255,1)",
  "--ComponentTempButtonPrimary3onColorBackground": "rgba(255,255,255,1)",
  "--ComponentTempButtonPrimary3onColorBackgroundpressed": "rgba(50,50,51,1)",
  "--ComponentTempButtonPrimary3onColorTextDefault": "rgba(0,0,0,1)",
  "--ComponentTempButtonPrimary3onColorTextPressed": "rgba(255,255,255,1)",
  "--ComponentTempButtonPrimary4Background": "rgba(0,0,0,1)",
  "--ComponentTempButtonPrimary4Backgroundpressed": "rgba(50,50,51,1)",
  "--ComponentTempButtonPrimary4TextDefault": "rgba(255,255,255,1)",
  "--ComponentTempButtonPrimary4TextPressed": "rgba(255,255,255,1)",
  "--ComponentTempButtonPrimary4onColorBackground": "rgba(255,255,255,1)",
  "--ComponentTempButtonPrimary4onColorBackgroundpressed": "rgba(50,50,51,1)",
  "--ComponentTempButtonPrimary4onColorTextDefault": "rgba(0,0,0,1)",
  "--ComponentTempButtonPrimary4onColorTextPressed": "rgba(255,255,255,1)",
  "--ComponentTempButtonPrimary5Background": "rgba(0,0,0,1)",
  "--ComponentTempButtonPrimary5Backgroundpressed": "rgba(50,50,51,1)",
  "--ComponentTempButtonPrimary5TextDefault": "rgba(255,255,255,1)",
  "--ComponentTempButtonPrimary5TextPressed": "rgba(255,255,255,1)",
  "--ComponentTempButtonPrimary5onColorBackground": "rgba(255,255,255,1)",
  "--ComponentTempButtonPrimary5onColorBackgroundpressed": "rgba(50,50,51,1)",
  "--ComponentTempButtonPrimary5onColorTextDefault": "rgba(0,0,0,1)",
  "--ComponentTempButtonPrimary5onColorTextPressed": "rgba(255,255,255,1)",
  "--ComponentTempBottomNavBackground": "rgba(255,255,255,1)",
  "--ComponentTempBottomNavTextDefault": "rgba(0,0,0,1)",
  "--ComponentTempBottomNavTextActive": "rgba(0,0,0,1)",
  "--ComponentTempBottomNavIconDefault": "rgba(0,0,0,1)",
  "--ComponentTempBottomNavIconActive": "rgba(0,0,0,1)",
  "--ComponentTempBottomNavUnderline": "rgba(11,226,72,1)",
  "--ComponentTempBottomNavContentTab1": "Home",
  "--ComponentTempBottomNavContentTab2": "Apply",
  "--ComponentTempBottomNavContentTab3": "Payments",
  "--ComponentTempBottomNavContentTab4": "Search",
  "--ComponentTempBottomNavContentTab5": "Cards",
  "--ComponentTempBottomNavContentShowTab5": 0,
  "--ComponentTempBottomNavDropshadowDefault": "rgba(0,0,0,0.06)",
  "--ComponentTempBottomNavDropshadowBlur": 0,
  "--ComponentTempBottomNavDropshadowXAxis": 0,
  "--ComponentTempBottomNavDropshadowYAxis": -1,
  "--ComponentTempCalendarHeaderBackground": "rgba(255,247,232,1)",
  "--ComponentTempCalendarHeaderText": "rgba(0,0,0,1)",
  "--ComponentTempCalendarHeaderBorder": "rgba(0,0,0,0)",
  "--ComponentTempCalendarMonthStepperBackground": "rgba(0,0,0,1)",
  "--ComponentTempCalendarQuickSelectionBackground": "rgba(255,255,255,1)",
  "--ComponentTempCalendarQuickSelectionText": "rgba(0,0,0,1)",
  "--ComponentTempCalendarQuickSelectionIcon": "rgba(0,0,0,1)",
  "--ComponentTempCalendarWheelPickerText": "rgba(0,0,0,1)",
  "--ComponentTempCalendarDayNamesBackground": "rgba(255,255,255,1)",
  "--ComponentTempCalendarDayNamesText": "rgba(118,118,118,1)",
  "--ComponentTempCalendarTodayBackgroundIndicator": "rgba(241,241,241,1)",
  "--ComponentTempCalendarTodayTextIndicator": "rgba(0,0,0,1)",
  "--ComponentTempCalendarDateBackground": "rgba(255,255,255,1)",
  "--ComponentTempCalendarDateTextDefault": "rgba(0,0,0,1)",
  "--ComponentTempCalendarDateTextPressed": "rgba(0,0,0,1)",
  "--ComponentTempCalendarDateTextDisabled": "rgba(118,118,118,1)",
  "--ComponentTempCalendarDateSelectedBackground": "rgba(0,0,0,1)",
  "--ComponentTempCalendarDateSelectedText": "rgba(255,255,255,1)",
  "--ComponentTempCardHubNotificationBannerBackground": "rgba(0,0,0,0.2)",
  "--ComponentTempCardHubBackground": "rgba(0,106,77,1)",
  "--ComponentTempCardHubActiveCardBackground": "rgba(0,63,46,1)",
  "--ComponentTempCardHubFrozenCardBackground": "rgba(173,173,173,1)",
  "--ComponentTempCardHubNewCardBadge": "rgba(13,85,149,1)",
  "--ComponentTempCardHubExpiringCardBadge": "rgba(118,118,118,1)",
  "--ComponentTempCardHubPartialFrozenCardBadge": "rgba(118,118,118,1)",
  "--ComponentTempCardHubPANText": "rgba(50,50,51,1)",
  "--ComponentTempCardHubCardHolderNameText": "rgba(255,255,255,1)",
  "--ComponentTempCardHubCardExpiryText": "rgba(255,255,255,1)",
  "--ComponentTempCardHubPartialPANText": "rgba(255,255,255,1)",
  "--ComponentTempCardHubCarBrandLogo": "rgba(255,255,255,1)",
  "--ComponentTempCardHubCarProviderLogo": "rgba(255,255,255,1)",
  "--ComponentTempCardHubNetworkLogo": "rgba(191,191,191,1)",
  "--ComponentTempCardHubCCVBackground": "rgba(255,255,255,1)",
  "--ComponentTempCardHubCCVText": "rgba(255,255,255,1)",
  "--ComponentTempCardHubMagnecticStrip": "rgba(0,0,0,1)",
  "--ComponentTempCardHubFullPANBackground": "rgba(255,255,255,1)",
  "--ComponentTempCardHubCardShadowDefault": "rgba(0,0,0,0.35)",
  "--ComponentTempCardHubCardShadowBlur": 24,
  "--ComponentTempCardHubCardShadowXAxis": 24,
  "--ComponentTempDividerDefault": "rgba(191,191,191,1)",
  "--ComponentTempEiaPinBorder": "rgba(50,50,51,1)",
  "--ComponentTempCardHubCardShadowYAxis": 4,
  "--ComponentTempEiaPinBackground": "rgba(255,255,255,1)",
  "--ComponentTempKeyboardBackground": "rgba(241,241,241,1)",
  "--ComponentTempKeyboardKeyBackground": "rgba(255,255,255,1)",
  "--ComponentTempKeyboardKeyBackgroundPressed": "rgba(255,255,255,1)",
  "--ComponentTempKeyboardKeyBackgroundPressediPad": "rgba(191,191,191,1)",
  "--ComponentTempKeyboardKeyText": "rgba(0,0,0,1)",
  "--ComponentTempKeyboardDeleteKeyBackground": "rgba(80,80,80,1)",
  "--ComponentTempKeyboardDeleteKeyIcon": "rgba(255,255,255,1)",
  "--ComponentTempKeyboardDeleteKeyIconPressed": "rgba(0,0,0,1)",
  "--ComponentTempKeyboardAccessoryBarBackground": "rgba(0,0,0,1)",
  "--ComponentTempKeyboardAccessoryBarText": "rgba(255,255,255,1)",
  "--ComponentTempListBackgroundpressed": "rgba(241,241,241,1)",
  "--ComponentTempMessageBorderWarningDefault": "rgba(0,0,0,0)",
  "--ComponentTempNotificationTagNewBackgroundDefault": "rgba(11,226,72,1)",
  "--ComponentTempNotificationPillGenericBackgroundDefault": "rgba(118,118,118,1)",
  "--ComponentTempNotificationPillGenericTextDefault": "rgba(255,255,255,1)",
  "--ComponentTempNotificationTagNewTextDefault": "rgba(0,0,0,1)",
  "--ComponentTempNotificationTagNewCornerradius": 200,
  "--ComponentTempNotificationPillWarningBackgroundDefault": "rgba(255,247,232,1)",
  "--ComponentTempNotificationPillWarningTextDefault": "rgba(0,0,0,1)",
  "--ComponentTempNotificationBadgeBackground": "rgba(219,15,48,1)",
  "--ComponentTempNotificationPanelCornerradius": 12,
  "--ComponentTempNotificationPanelArrowShape01": 0,
  "--ComponentTempNotificationPanelArrowShape02": 0,
  "--ComponentTempNotificationPanelArrowNeg01Spacing": -1,
  "--ComponentTempNotificationPanelArrowNeg02Spacing": -2,
  "--ComponentTempPopupHeaderDefaultBackground": "rgba(241,241,241,1)",
  "--ComponentTempPopupHeaderPositiveBackground": "rgba(241,241,241,1)",
  "--ComponentTempPopupHeaderNegativeBackground": "rgba(219,15,48,1)",
  "--ComponentTempPopupHeaderFraudBackground": "rgba(224,105,0,1)",
  "--ComponentTempPopupHeaderBottomBorderWidth": 0,
  "--ComponentTempPopupInformationPanelBackground": "rgba(255,247,232,1)",
  "--ComponentTempPopupInformationPanelText": "rgba(0,0,0,1)",
  "--ComponentTempPopupTitleDefault": "rgba(0,0,0,1)",
  "--ComponentTempPopupTitlePositive": "rgba(0,0,0,1)",
  "--ComponentTempPopupTitleNegative": "rgba(255,255,255,1)",
  "--ComponentTempPopupTitleFraud": "rgba(0,0,0,1)",
  "--ComponentTempPopupCornerRadius": 16,
  "--ComponentTempPopupButtonBackground": "rgba(255,255,255,1)",
  "--ComponentTempPopupButtonBackgroundPressed": "rgba(201,201,201,1)",
  "--ComponentTempPopupButtonBackgroundDisabled": "rgba(241,241,241,1)",
  "--ComponentTempPopupButtonBorderDefault": "rgba(201,201,201,1)",
  "--ComponentTempPopupButtonTextDefault": "rgba(0,0,0,1)",
  "--ComponentTempPopupButtonTextPressed": "rgba(0,0,0,1)",
  "--ComponentTempPopupButtonTextDisabled": "rgba(118,118,118,1)",
  "--ComponentTempScrollIndicator": "rgba(0,0,0,1)",
  "--ComponentTempLinearProgressIndicatorTrack": "rgba(11,226,72,1)",
  "--ComponentTempStepProgressIndicatorCompleted": "rgba(0,0,0,1)",
  "--ComponentTempStepProgressIndicatorDefault": "rgba(201,201,201,1)",
  "--ComponentTempSpinnerDefault": "rgba(0,0,0,1)",
  "--ComponentTempSpinnerDefaultAlt01": "rgba(255,255,255,1)",
  "--ComponentTempSpinnerHighlight": "rgba(11,226,72,1)",
  "--ComponentTempSpinnerHighlightAlt01": "rgba(11,226,72,1)",
  "--ComponentTempSpinnerIcon": "rgba(0,0,0,1)",
  "--ComponentTempSpinnerGradientStop01": "rgba(0,0,0,0)",
  "--ComponentTempSpinnerGradientStop02": "rgba(0,0,0,1)",
  "--ComponentTempSwitchPulse": "rgba(50,50,51,0.24)",
  "--ComponentTempSpinnerGradientAlt01Stop01": "rgba(0,0,0,0)",
  "--ComponentTempSpinnerGradientAlt01Stop02": "rgba(0,0,0,1)",
  "--ComponentTempSwitchHandleDefault": "rgba(0,0,0,1)",
  "--ComponentTempSwitchHandelDefaultSize": 16,
  "--ComponentTempSwitchHandlePressed": "rgba(50,50,51,1)",
  "--ComponentTempSwitchHandlePressedSize": 28,
  "--ComponentTempSwitchHandleDisabled": "rgba(118,118,118,1)",
  "--ComponentTempSwitchHandleDisbledSize": 16,
  "--ComponentTempSwitchHandleSelected": "rgba(255,255,255,1)",
  "--ComponentTempSwitchHandleSelectedSize": 24,
  "--ComponentTempSwitchHandleSelectedPressed": "rgba(255,255,255,1)",
  "--ComponentTempSwitchHandleSelectedPressedSize": 24,
  "--ComponentTempSwitchHandleSelectedDisabled": "rgba(118,118,118,1)",
  "--ComponentTempSwitchHandleSelectedDisabledSize": 24,
  "--ComponentTempSwitchIconSelectedDefault": "rgba(0,0,0,1)",
  "--ComponentTempSwitchIconSelectedPressed": "rgba(0,0,0,1)",
  "--ComponentTempSwitchIconSelectedDisabled": "rgba(0,0,0,1)",
  "--ComponentTempSwitchTrackBackgroundDefault": "rgba(255,255,255,1)",
  "--ComponentTempSwitchTrackBackgroundDefaultAlt01": "rgba(201,201,201,1)",
  "--ComponentTempSwitchTrackBackgroundPressed": "rgba(255,255,255,1)",
  "--ComponentTempSwitchTrackBackgroundDisabled": "rgba(201,201,201,1)",
  "--ComponentTempSwitchTrackBackgroundSelectedDefault": "rgba(0,0,0,1)",
  "--ComponentTempSwitchTrackBackgroundSelectedPressed": "rgba(0,0,0,1)",
  "--ComponentTempSwitchTrackBackgroundSelectedDisabled": "rgba(201,201,201,1)",
  "--ComponentTempSwitchTrackBorderDefault": "rgba(50,50,51,1)",
  "--ComponentTempSwitchTrackBorderPressed": "rgba(50,50,51,1)",
  "--ComponentTempSwitchTrackBorderDisabled": "rgba(201,201,201,1)",
  "--ComponentTempSwitchTrackBorderSelected": "rgba(0,0,0,0)",
  "--ComponentTempSwitchTrackBorderSelectedPressed": "rgba(0,0,0,0)",
  "--ComponentTempSwitchTrackBorderSelectedDisabled": "rgba(0,0,0,0)",
  "--ComponentTempToggleBackgroundDefault": "rgba(241,241,241,1)",
  "--ComponentTempToggleBackgroundActive": "rgba(0,0,0,1)",
  "--ComponentTempToggleBackgroundActiveDisabled": "rgba(201,201,201,1)",
  "--ComponentTempToggleBorderDefault": "rgba(0,0,0,1)",
  "--ComponentTempToggleBorderDisabled": "rgba(201,201,201,1)",
  "--ComponentTempToggleTextDefault": "rgba(255,255,255,1)",
  "--ComponentTempToggleCornerRadiusDefault": 8,
  "--ComponentTempToggleCornerRadiusLarge": 12,
  "--ComponentTempTableSpacerBackground": "rgba(0,0,0,1)",
  "--ComponentTempTabsBackgroundDefault": "rgba(241,241,241,1)",
  "--ComponentTempTabsBackgroundActive": "rgba(255,255,255,1)",
  "--ComponentTempTabsBackgroundActiveAlt01": "rgba(0,0,0,0)",
  "--ComponentTempTabsBorderDefault": "rgba(0,0,0,1)",
  "--ComponentTempTabsBorderActive": "rgba(0,0,0,1)",
  "--ComponentTempTabsBorderActiveAlt01": "rgba(0,0,0,1)",
  "--ComponentTempTabsTextDefault": "rgba(0,0,0,1)",
  "--ComponentTempTabsTextDefaultAlt01": "rgba(0,0,0,1)",
  "--ComponentTempTabsTextActive": "rgba(0,0,0,1)",
  "--ComponentTempTabsTextActiveAlt01": "rgba(0,0,0,1)",
  "--ComponentTempTabsIconDefault": "rgba(0,0,0,1)",
  "--ComponentTempTabsIconActive": "rgba(0,0,0,1)",
  "--ComponentTempTileBackgroundDefault": "rgba(255,255,255,1)",
  "--ComponentTempTileBackgroundPressed": "rgba(201,201,201,1)",
  "--ComponentTempTileBorderDefault": "rgba(0,0,0,0)",
  "--ComponentTempTileBorderPressed": "rgba(0,0,0,0)",
  "--ComponentTempTileTextDefault": "rgba(0,0,0,1)",
  "--ComponentTempTileTextPressed": "rgba(0,0,0,1)",
  "--ComponentTempTileIconDefault": "rgba(0,0,0,1)",
  "--ComponentTempTileIconPressed": "rgba(0,0,0,1)",
  "--ComponentTempTileCornerRadius": 12,
  "--ComponentTempTrayHandle": "rgba(0,0,0,1)",
  "--ComponentTempTrayHandleAlt01": "rgba(255,255,255,1)",
  "--ComponentTempQuickActionBackgroundDefault": "rgba(255,255,255,1)",
  "--ComponentTempQuickActionBackgroundDefaultAlt01": "rgba(255,255,255,1)",
  "--ComponentTempQuickActionBackgroundPressed": "rgba(201,201,201,1)",
  "--ComponentTempQuickActionBackgroundDisabled": "rgba(241,241,241,1)",
  "--ComponentTempQuickActionBorderDefault": "rgba(201,201,201,1)",
  "--ComponentTempQuickActionBorderPressed": "rgba(201,201,201,1)",
  "--ComponentTempQuickActionBorderDisabled": "rgba(201,201,201,1)",
  "--ComponentTempQuickActionTextDefault": "rgba(0,0,0,1)",
  "--ComponentTempQuickActionTextPressed": "rgba(0,0,0,1)",
  "--ComponentTempQuickActionTextDisabled": "rgba(201,201,201,1)",
  "--ComponentTempQuickActionIconDefault": "rgba(0,0,0,1)",
  "--ComponentTempQuickActionIconDefaultAlt01": "rgba(0,0,0,1)",
  "--ComponentTempQuickActionIconPressed": "rgba(0,0,0,1)",
  "--ComponentTempQuickActionIconDisabled": "rgba(201,201,201,1)",
  "--ComponentTempQuickActionBorderwidth": 1,
  "--ComponentTempQuickActionBorderwidthAlt01": 1,
  "--ComponentTempQuickActionCornerRadiusDefault": 12,
  "--ComponentTempQuickActionCornerRadiusLarge": 12,
  "--ComponentTempQuickActionShapeDefault": 0,
  "--ComponentTempQuickActionShapeDefaultAlt01": 0,
  "--ComponentTempQuickActionShapeDefaultAlt02": 0,
  "--ComponentTempUIViewBorderDefault": "rgba(0,0,0,1)",
  "--TypesStyle1LetterSpacing": 0,
  "--TypesStyle1iOSClassification": "Large-Title",
  "--ComponentCardHubCardCornerRadius": 8,
  "--ComponentSpacesAccountTileDropShadowDefault": "rgba(0,0,0,0.05)",
  "--ComponentSpacesAccountTileDropShadowBlur": 20,
  "--ComponentSpacesAccountTileDropShadowXAxis": 0,
  "--ComponentSpacesAccountTileDropShadowYAxis": 4,
  "--ComponentCardHubCardTagCornerRadius": 200,
  "--ComponentCardHubCardDropShadowDefault": "rgba(0,0,0,0.25)",
  "--ComponentCardHubCardDropShadowBlur": 24,
  "--ComponentCardHubCardDropShadowXAxis": 0,
  "--ComponentCardHubCardDropShadowYAxis": 4,
  "--ComponentCardHubLloydsCardTagNewBackground": "rgba(11,226,72,1)",
  "--ComponentCardHubLloydsCardTagNewText": "rgba(0,0,0,1)",
  "--ComponentCardHubLloydsCardTagReplacedBackground": "rgba(11,226,72,1)",
  "--ComponentCardHubLloydsCardTagReplacedText": "rgba(0,0,0,1)",
  "--ComponentCardHubLloydsCardTagPartFrozenBackground": "rgba(0,0,0,1)",
  "--ComponentCardHubLloydsCardTagPartFrozenText": "rgba(255,255,255,1)",
  "--ComponentCardHubLloydsCardTagExpiringBackground": "rgba(0,0,0,1)",
  "--ComponentCardHubLloydsCardTagExpiringText": "rgba(255,255,255,1)",
  "--ComponentCardHubLloydsCardTagBlockedBackground": "rgba(0,0,0,1)",
  "--ComponentCardHubLloydsCardTagBlockedText": "rgba(255,255,255,1)",
  "--ComponentCardHubLloydsCardActiveBackground": "rgba(17,182,122,1)",
  "--ComponentCardHubLloydsCardActiveText": "rgba(0,0,0,1)",
  "--ComponentCardHubLloydsCardActiveLogo": "rgba(0,0,0,1)",
  "--ComponentCardHubLloydsCardFrozenBackground": "rgba(201,201,201,1)",
  "--ComponentCardHubLloydsCardFrozenText": "rgba(0,0,0,1)",
  "--ComponentCardHubLloydsCardFrozenLogo": "rgba(0,0,0,1)",
  "--ComponentCardHubLloydsCardFrozenIllustration": "rgba(241,241,241,0.5)",
  "--ComponentCardHubLloydsCardBlockedBackground": "rgba(201,201,201,1)",
  "--ComponentCardHubLloydsCardBlockedText": "rgba(0,0,0,1)",
  "--ComponentCardHubLloydsCardBlockedLogo": "rgba(0,0,0,1)",
  "--ComponentCardHubLloydsCardBlockedIllustration": "rgba(241,241,241,0.5)",
  "--ComponentCardHubLloydsCardErrorBackground": "rgba(255,255,255,1)",
  "--ComponentCardHubLloydsCardDetailsCardNumberBackground": "rgba(0,0,0,1)",
  "--ComponentCardHubLloydsCardDetailsCardNumberText": "rgba(255,255,255,1)",
  "--ComponentCardHubLloydsCardDetailsCardNumberIcon": "rgba(255,255,255,1)",
  "--ComponentCardHubLloydsCardDetailsMagneticStrip": "rgba(0,0,0,1)",
  "--ComponentCardHubLloydsCardDetailsCVVBackground": "rgba(255,255,255,1)",
  "--ComponentCardHubLloydsCardDetailsCVVText": "rgba(0,0,0,1)",
  "--ComponentCardHubLloydsCardDetailsNetworkLogo": "rgba(201,201,201,1)",
  "--ComponentCardHubHalifaxCardTagNewBackground": "rgba(204,0,74,1)",
  "--ComponentCardHubHalifaxCardTagNewText": "rgba(255,255,255,1)",
  "--ComponentCardHubHalifaxCardTagReplacedBackground": "rgba(0,129,255,1)",
  "--ComponentCardHubHalifaxCardTagReplacedText": "rgba(255,255,255,1)",
  "--ComponentCardHubHalifaxCardTagPartFrozenBackground": "rgba(65,77,102,1)",
  "--ComponentCardHubHalifaxCardTagPartFrozenText": "rgba(255,255,255,1)",
  "--ComponentCardHubHalifaxCardTagExpiringBackground": "rgba(65,77,102,1)",
  "--ComponentCardHubHalifaxCardTagExpiringText": "rgba(255,255,255,1)",
  "--ComponentCardHubHalifaxCardTagBlockedBackground": "rgba(65,77,102,1)",
  "--ComponentCardHubHalifaxCardTagBlockedText": "rgba(255,255,255,1)",
  "--ComponentCardHubHalifaxCardActiveBackground": "rgba(7,29,73,1)",
  "--ComponentCardHubHalifaxCardActiveText": "rgba(255,255,255,1)",
  "--ComponentCardHubHalifaxCardActiveLogo": "rgba(255,255,255,1)",
  "--ComponentCardHubHalifaxCardFrozenBackground": "rgba(131,142,164,1)",
  "--ComponentCardHubHalifaxCardFrozenText": "rgba(7,29,73,1)",
  "--ComponentCardHubHalifaxCardFrozenLogo": "rgba(7,29,73,1)",
  "--ComponentCardHubHalifaxCardFrozenIllustration": "rgba(241,241,241,0.5)",
  "--ComponentCardHubHalifaxCardBlockedBackground": "rgba(131,142,164,1)",
  "--ComponentCardHubHalifaxCardBlockedText": "rgba(7,29,73,1)",
  "--ComponentCardHubHalifaxCardBlockedLogo": "rgba(7,29,73,1)",
  "--ComponentCardHubHalifaxCardBlockedIllustration": "rgba(241,241,241,0.5)",
  "--ComponentCardHubHalifaxCardErrorBackground": "rgba(255,255,255,1)",
  "--ComponentCardHubHalifaxCardDetailsCardNumberBackground": "rgba(0,94,184,1)",
  "--ComponentCardHubHalifaxCardDetailsCardNumberText": "rgba(255,255,255,1)",
  "--ComponentCardHubHalifaxCardDetailsCardNumberIcon": "rgba(255,255,255,1)",
  "--ComponentCardHubHalifaxCardDetailsMagneticStrip": "rgba(0,94,184,1)",
  "--ComponentCardHubHalifaxCardDetailsCVVBackground": "rgba(255,255,255,1)",
  "--ComponentCardHubHalifaxCardDetailsCVVText": "rgba(7,29,73,1)",
  "--ComponentCardHubHalifaxCardDetailsNetworkLogo": "rgba(201,201,201,1)",
  "--ComponentCardHubBoSCardTagNewBackground": "rgba(224,43,82,1)",
  "--ComponentCardHubBoSCardTagNewText": "rgba(255,255,255,1)",
  "--ComponentCardHubBoSCardTagReplacedBackground": "rgba(21,126,179,1)",
  "--ComponentCardHubBoSCardTagReplacedText": "rgba(255,255,255,1)",
  "--ComponentCardHubBoSCardTagPartFrozenBackground": "rgba(118,118,118,1)",
  "--ComponentCardHubBoSCardTagPartFrozenText": "rgba(255,255,255,1)",
  "--ComponentCardHubBoSCardTagExpiringBackground": "rgba(118,118,118,1)",
  "--ComponentCardHubBoSCardTagExpiringText": "rgba(255,255,255,1)",
  "--ComponentCardHubBoSCardTagBlockedBackground": "rgba(118,118,118,1)",
  "--ComponentCardHubBoSCardTagBlockedText": "rgba(255,255,255,1)",
  "--ComponentCardHubBoSCardActiveBackground": "rgba(5,40,106,1)",
  "--ComponentCardHubBoSCardActiveText": "rgba(255,255,255,1)",
  "--ComponentCardHubBoSCardActiveLogo": "rgba(255,255,255,1)",
  "--ComponentCardHubBoSCardFrozenBackground": "rgba(173,173,173,1)",
  "--ComponentCardHubBoSCardFrozenText": "rgba(51,51,51,1)",
  "--ComponentCardHubBoSCardFrozenLogo": "rgba(51,51,51,1)",
  "--ComponentCardHubBoSCardFrozenIllustration": "rgba(241,241,241,0.5)",
  "--ComponentCardHubBoSCardBlockedBackground": "rgba(173,173,173,1)",
  "--ComponentCardHubBoSCardBlockedText": "rgba(51,51,51,1)",
  "--ComponentCardHubBoSCardBlockedLogo": "rgba(51,51,51,1)",
  "--ComponentCardHubBoSCardBlockedIllustration": "rgba(241,241,241,0.5)",
  "--ComponentCardHubBoSCardErrorBackground": "rgba(255,255,255,1)",
  "--ComponentCardHubBoSCardDetailsCardNumberBackground": "rgba(0,91,162,1)",
  "--ComponentCardHubBoSCardDetailsCardNumberText": "rgba(255,255,255,1)",
  "--ComponentCardHubBoSCardDetailsCardNumberIcon": "rgba(255,255,255,1)",
  "--ComponentCardHubBoSCardDetailsMagneticStrip": "rgba(0,91,162,1)",
  "--ComponentCardHubBoSCardDetailsCVVBackground": "rgba(255,255,255,1)",
  "--ComponentCardHubBoSCardDetailsCVVText": "rgba(51,51,51,1)",
  "--ComponentCardHubBoSCardDetailsNetworkLogoBackground": "rgba(201,201,201,1)",
  "--ComponentCardHubMBNACardTagCornerRadius": 200,
  "--ComponentCardHubMBNACardTagNewBackground": "rgba(219,21,0,1)",
  "--ComponentCardHubMBNACardTagNewText": "rgba(255,255,255,1)",
  "--ComponentCardHubMBNACardTagReplacedBackground": "rgba(94,147,219,1)",
  "--ComponentCardHubMBNACardTagReplacedText": "rgba(255,255,255,1)",
  "--ComponentCardHubMBNACardTagPartFrozenBackground": "rgba(118,118,118,1)",
  "--ComponentCardHubMBNACardTagPartFrozenText": "rgba(255,255,255,1)",
  "--ComponentCardHubMBNACardTagExpiringBackground": "rgba(118,118,118,1)",
  "--ComponentCardHubMBNACardTagExpiringText": "rgba(255,255,255,1)",
  "--ComponentCardHubMBNACardTagBlockedBackground": "rgba(118,118,118,1)",
  "--ComponentCardHubMBNACardTagBlockedText": "rgba(255,255,255,1)",
  "--ComponentCardHubMBNACardActiveBackground": "rgba(0,40,76,1)",
  "--ComponentCardHubMBNACardActiveText": "rgba(255,255,255,1)",
  "--ComponentCardHubMBNACardActiveLogo": "rgba(255,255,255,1)",
  "--ComponentCardHubMBNACardFrozenBackground": "rgba(173,173,173,1)",
  "--ComponentCardHubMBNACardFrozenText": "rgba(51,51,51,1)",
  "--ComponentCardHubMBNACardFrozenLogo": "rgba(51,51,51,1)",
  "--ComponentCardHubMBNACardFrozenIllustration": "rgba(241,241,241,0.5)",
  "--ComponentCardHubMBNACardBlockedBackground": "rgba(173,173,173,1)",
  "--ComponentCardHubMBNACardBlockedText": "rgba(51,51,51,1)",
  "--ComponentCardHubMBNACardBlockedLogo": "rgba(51,51,51,1)",
  "--ComponentCardHubMBNACardBlockedIllustration": "rgba(241,241,241,0.5)",
  "--ComponentCardHubMBNACardErrorBackground": "rgba(255,255,255,1)",
  "--ComponentCardHubMBNACardDetailsCardNumberBackground": "rgba(16,121,135,1)",
  "--ComponentCardHubMBNACardDetailsCardNumberText": "rgba(255,255,255,1)",
  "--ComponentCardHubMBNACardDetailsCardNumberIcon": "rgba(255,255,255,1)",
  "--ComponentCardHubMBNACardDetailsMagneticStrip": "rgba(54,92,125,1)",
  "--ComponentCardHubMBNACardDetailsCVVBackground": "rgba(255,255,255,1)",
  "--ComponentCardHubMBNACardDetailsCVVText": "rgba(51,51,51,1)",
  "--ComponentCardHubMBNACardDetailsNetworkLogo": "rgba(201,201,201,1)",
  "--ComponentCardHubCarouselIndicatorSizeDefault": 8,
  "--ComponentCardHubCarouselIndicatorSizeActive": 12,
  "--Brandtheme": "Lloyds-- V2",
  "--Illustrationtheme": "Lloyds-- V2",
  "--BorderGenericDefault": "rgba(241,241,241,1)",
  "--BorderPanelDefault": "rgba(0,0,0,0)",
  "--BorderActionDefault": "rgba(0,0,0,1)",
  "--BorderActionDefaultAlt01": "rgba(0,0,0,0)",
  "--BorderActionPressed": "rgba(50,50,51,1)",
  "--BorderActionDisabled": "rgba(201,201,201,1)",
  "--BorderActionOnColorDefault": "rgba(255,255,255,1)",
  "--BorderActionOnColorDefaultAlt01": "rgba(0,0,0,0)",
  "--BorderActionOnColorPressed": "rgba(50,50,51,1)",
  "--BorderActionOnColorDisabled": "rgba(201,201,201,1)",
  "--BorderGenericDefaultAlt01": "rgba(201,201,201,1)",
  "--BorderGenericDefaultAlt02": "rgba(0,0,0,1)",
  "--BorderGenericInverse": "rgba(255,255,255,1)",
  "--BorderGenericBrand": "rgba(11,226,72,1)",
  "--BorderGenericBrandAlt01": "rgba(11,226,72,1)",
  "--BorderSentimentCritical": "rgba(219,15,48,1)",
  "--BorderSentimentCriticalAlt01": "rgba(0,0,0,0)",
  "--BorderSentimentWarning": "rgba(224,105,0,1)",
  "--BorderSentimentWarningAlt01": "rgba(0,0,0,0)",
  "--BorderSentimentSuccess": "rgba(15,159,106,1)",
  "--BorderSentimentSuccessAlt01": "rgba(0,0,0,0)",
  "--BorderSentimentInfo": "rgba(39,106,230,1)",
  "--BorderSentimentInfoAlt01": "rgba(0,0,0,0)",
  "--BorderInputDefault": "rgba(50,50,51,1)",
  "--BorderInputActive": "rgba(0,0,0,1)",
  "--BorderInputDisabled": "rgba(201,201,201,1)",
  "--BorderInputCritical": "rgba(219,15,48,1)",
  "--BorderInputSuccess": "rgba(16,168,112,1)",
  "--TypesStyle1Max160FontFamily": "GT-Ultra Median",
  "--TypesStyle1Max160FontWeight": "Bold",
  "--TypesStyle1Max160FontSize": 29,
  "--TypesStyle1Max160LineHeight": 32,
  "--TypesStyle1Max160LineSpacing": 32,
  "--TypesStyle1Max160LetterSpacing": 0,
  "--TypesStyle1Max160iOSClassification": "Large-Title",
  "--TypesStyle1Max135FontFamily": "GT-Ultra Median",
  "--TypesStyle1Max135FontWeight": "Bold",
  "--TypesStyle1Max135FontSize": 29,
  "--TypesStyle1Max135LineHeight": 32,
  "--TypesStyle1Max135LineSpacing": 32,
  "--TypesStyle1Max135LetterSpacing": 0,
  "--TypesStyle1Max135iOSClassification": "Large-Title",
  "--TypesStyle1Max100FontFamily": "GT-Ultra Median",
  "--TypesStyle1BFontFamily": "GT-Ultra",
  "--TypesStyle1BFontWeight": "Regular",
  "--TypesStyle1BFontSize": 29,
  "--TypesStyle1BLineHeight": 32,
  "--TypesStyle1BLineSpacing": 32,
  "--TypesStyle1BLetterSpacing": 0,
  "--TypesStyle1BiOSClassification": "Large-Title",
  "--TypesStyle1BMax160FontFamily": "GT-Ultra",
  "--TypesStyle1BMax160FontWeight": "Regular",
  "--TypesStyle1BMax160FontSize": 29,
  "--TypesStyle1BMax160LineHeight": 32,
  "--TypesStyle1BMax160LineSpacing": 32,
  "--TypesStyle1BMax160LetterSpacing": 0,
  "--TypesStyle1BMax160iOSClassification": "Large-Title",
  "--TypesStyle1BMax135FontFamily": "GT-Ultra",
  "--TypesStyle1BMax135FontWeight": "Regular",
  "--TypesStyle1BMax135FontSize": 29,
  "--TypesStyle1BMax135LineHeight": 32,
  "--TypesStyle1BMax135LineSpacing": 32,
  "--TypesStyle1BMax135LetterSpacing": 0,
  "--TypesStyle1BMax135iOSClassification": "Large-Title",
  "--TypesStyle1BMax100FontFamily": "GT-Ultra",
  "--TypesStyle1BMax100FontWeight": "Regular",
  "--TypesStyle1BMax100FontSize": 29,
  "--TypesStyle1BMax100LineHeight": 32,
  "--TypesStyle1BMax100LineSpacing": 32,
  "--TypesStyle1BMax100LetterSpacing": 0,
  "--TypesStyle1BMax100iOSClassification": "Large-Title",
  "--TypesStyle1Max100FontWeight": "Bold",
  "--TypesStyle1Max100FontSize": 29,
  "--TypesStyle1Max100LineHeight": 32,
  "--TypesStyle1Max100LineSpacing": 32,
  "--TypesStyle1Max100LetterSpacing": 0,
  "--TypesStyle1Max100iOSClassification": "Large-Title",
  "--TypesStyle2FontFamily": "GT-Ultra Median",
  "--TypesStyle2Max160FontFamily": "GT-Ultra Median",
  "--TypesStyle2Max135FontFamily": "GT-Ultra Median",
  "--TypesStyle2Max100FontFamily": "GT-Ultra Median",
  "--TypesStyle2BFontFamily": "GT-Ultra",
  "--TypesStyle2BFontWeight": "Regular",
  "--TypesStyle2BFontSize": 23,
  "--TypesStyle2BLineHeight": 26,
  "--TypesStyle2BLineSpacing": 26,
  "--TypesStyle2BLetterSpacing": 0,
  "--TypesStyle2BiOSClassification": "Title-1",
  "--TypesStyle2BMax160FontFamily": "GT-Ultra",
  "--TypesStyle2BMax160FontWeight": "Regular",
  "--TypesStyle2BMax160FontSize": 23,
  "--TypesStyle2BMax160LineHeight": 26,
  "--TypesStyle2BMax160LineSpacing": 26,
  "--TypesStyle2BMax160LetterSpacing": 0,
  "--TypesStyle2BMax160iOSClassification": "Title-1",
  "--TypesStyle2BMax135FontFamily": "GT-Ultra",
  "--TypesStyle2BMax135FontWeight": "Regular",
  "--TypesStyle2BMax135FontSize": 23,
  "--TypesStyle2BMax135LineHeight": 26,
  "--TypesStyle2BMax135LineSpacing": 26,
  "--TypesStyle2BMax135LetterSpacing": 0,
  "--TypesStyle2BMax135iOSClassification": "Title-1",
  "--TypesStyle2BMax100FontFamily": "GT-Ultra",
  "--TypesStyle2BMax100FontWeight": "Regular",
  "--TypesStyle2BMax100FontSize": 23,
  "--TypesStyle2BMax100LineHeight": 26,
  "--TypesStyle2BMax100LineSpacing": 26,
  "--TypesStyle2BMax100LetterSpacing": 0,
  "--TypesStyle2BMax100iOSClassification": "Title-1",
  "--TypesStyle2Max100FontWeight": "Bold",
  "--TypesStyle2Max100FontSize": 23,
  "--TypesStyle2Max100LineHeight": 26,
  "--TypesStyle2Max100LineSpacing": 26,
  "--TypesStyle2Max100LetterSpacing": 0,
  "--TypesStyle2Max100iOSClassification": "Title-1",
  "--TypesStyle2Max135FontWeight": "Bold",
  "--TypesStyle2Max135FontSize": 23,
  "--TypesStyle2Max135LineHeight": 26,
  "--TypesStyle2Max135LineSpacing": 26,
  "--TypesStyle2Max135LetterSpacing": 0,
  "--TypesStyle2Max135iOSClassification": "Title-1",
  "--TypesStyle2Max160FontWeight": "Bold",
  "--TypesStyle2Max160FontSize": 23,
  "--TypesStyle2Max160LineHeight": 26,
  "--TypesStyle2Max160LineSpacing": 26,
  "--TypesStyle2Max160LetterSpacing": 0,
  "--TypesStyle2Max160iOSClassification": "Title-1",
  "--TypesStyle2FontWeight": "Bold",
  "--TypesStyle2FontSize": 23,
  "--TypesStyle2LineHeight": 26,
  "--TypesStyle2LineSpacing": 26,
  "--TypesStyle2LetterSpacing": 0,
  "--TypesStyle2iOSClassification": "Title-1",
  "--TypesStyle3FontFamily": "GT-Ultra Median",
  "--TypesStyle3Max160FontFamily": "GT-Ultra Median",
  "--TypesStyle3Max160FontWeight": "Bold",
  "--TypesStyle3Max160FontSize": 19,
  "--TypesStyle3Max160LineHeight": 22,
  "--TypesStyle3Max160LineSpacing": 22,
  "--TypesStyle3Max160LetterSpacing": 0,
  "--TypesStyle3Max160iOSClassification": "Title-2",
  "--TypesStyle3Max135FontFamily": "GT-Ultra Median",
  "--TypesStyle3Max135FontWeight": "Bold",
  "--TypesStyle3Max135FontSize": 19,
  "--TypesStyle3Max135LineHeight": 22,
  "--TypesStyle3Max135LineSpacing": 22,
  "--TypesStyle3Max135LetterSpacing": 0,
  "--TypesStyle3Max135iOSClassification": "Title-2",
  "--TypesStyle3Max100FontFamily": "GT-Ultra Median",
  "--TypesStyle3BFontFamily": "GT-Ultra",
  "--TypesStyle3BFontWeight": "Regular",
  "--TypesStyle3BFontSize": 19,
  "--TypesStyle3BLineHeight": 22,
  "--TypesStyle3BLineSpacing": 22,
  "--TypesStyle3BLetterSpacing": -0.20000000298023224,
  "--TypesStyle3BiOSClassification": "Title-2",
  "--TypesStyle3BMax160FontFamily": "GT-Ultra",
  "--TypesStyle3BMax160FontWeight": "Regular",
  "--TypesStyle3BMax160FontSize": 19,
  "--TypesStyle3BMax160LineHeight": 22,
  "--TypesStyle3BMax160LineSpacing": 22,
  "--TypesStyle3BMax160LetterSpacing": 0,
  "--TypesStyle3BMax160iOSClassification": "Title-2",
  "--TypesStyle3BMax135FontFamily": "GT-Ultra",
  "--TypesStyle3BMax135FontWeight": "Regular",
  "--TypesStyle3BMax135FontSize": 19,
  "--TypesStyle3BMax135LineHeight": 22,
  "--TypesStyle3BMax135LineSpacing": 22,
  "--TypesStyle3BMax135LetterSpacing": 0,
  "--TypesStyle3BMax135iOSClassification": "Title-2",
  "--TypesStyle3BMax100FontFamily": "GT-Ultra",
  "--TypesStyle3BMax100FontWeight": "Regular",
  "--TypesStyle3BMax100FontSize": 19,
  "--TypesStyle3BMax100LineHeight": 22,
  "--TypesStyle3BMax100LineSpacing": 22,
  "--TypesStyle3BMax100LetterSpacing": 0,
  "--TypesStyle3BMax100iOSClassification": "Title-2",
  "--TypesStyle3Max100FontWeight": "Bold",
  "--TypesStyle3Max100FontSize": 19,
  "--TypesStyle3Max100LineHeight": 22,
  "--TypesStyle3Max100LineSpacing": 22,
  "--TypesStyle3Max100LetterSpacing": 0,
  "--TypesStyle3Max100iOSClassification": "Title-2",
  "--TypesStyle4FontFamily": "GT-Ultra",
  "--TypesStyle4Max160FontFamily": "GT-Ultra",
  "--TypesStyle4Max160FontWeight": "Bold",
  "--TypesStyle4Max160FontSize": 17,
  "--TypesStyle4Max160LineHeight": 22,
  "--TypesStyle4Max160LineSpacing": 22,
  "--TypesStyle4Max160LetterSpacing": 0,
  "--TypesStyle4Max160iOSClassification": "Headline",
  "--TypesStyle4Max135FontFamily": "GT-Ultra",
  "--TypesStyle4Max135FontWeight": "Bold",
  "--TypesStyle4Max135FontSize": 17,
  "--TypesStyle4Max135LineHeight": 22,
  "--TypesStyle4Max135LineSpacing": 22,
  "--TypesStyle4Max135LetterSpacing": 0,
  "--TypesStyle4Max135iOSClassification": "Headline",
  "--TypesStyle4Max100FontFamily": "GT-Ultra",
  "--TypesStyle4Max100FontWeight": "Bold",
  "--TypesStyle4Max100FontSize": 17,
  "--TypesStyle4Max100LineHeight": 22,
  "--TypesStyle4Max100LineSpacing": 22,
  "--TypesStyle4Max100LetterSpacing": 0,
  "--TypesStyle4Max100iOSClassification": "Headline",
  "--TypesStyle4FontWeight": "Bold",
  "--TypesStyle4FontSize": 17,
  "--TypesStyle4LineHeight": 22,
  "--TypesStyle4LineSpacing": 22,
  "--TypesStyle4LetterSpacing": 0,
  "--TypesStyle4iOSClassification": "Headline",
  "--TypesStyle3FontWeight": "Bold",
  "--TypesStyle3FontSize": 19,
  "--TypesStyle3LineHeight": 22,
  "--TypesStyle3LineSpacing": 22,
  "--TypesStyle3LetterSpacing": -0.20000000298023224,
  "--TypesStyle3iOSClassification": "Title-2",
  "--TypesStyle5FontFamily": "GT-Ultra",
  "--TypesStyle5Max160FontFamily": "GT-Ultra",
  "--TypesStyle5Max160FontWeight": "Regular",
  "--TypesStyle5Max160FontSize": 17,
  "--TypesStyle5Max160LineHeight": 22,
  "--TypesStyle5Max160LineSpacing": 22,
  "--TypesStyle5Max160LetterSpacing": 0,
  "--TypesStyle5Max160iOSClassification": "Body",
  "--TypesStyle5Max135FontFamily": "GT-Ultra",
  "--TypesStyle5Max135FontWeight": "Regular",
  "--TypesStyle5Max135FontSize": 17,
  "--TypesStyle5Max135LineHeight": 22,
  "--TypesStyle5Max135LineSpacing": 22,
  "--TypesStyle5Max135LetterSpacing": 0,
  "--TypesStyle5Max135iOSClassification": "Body",
  "--TypesStyle5Max100FontFamily": "GT-Ultra",
  "--TypesStyle5Max100FontWeight": "Regular",
  "--TypesStyle5Max100FontSize": 17,
  "--TypesStyle5Max100LineHeight": 22,
  "--TypesStyle5Max100LineSpacing": 22,
  "--TypesStyle5Max100LetterSpacing": 0,
  "--TypesStyle5Max100iOSClassification": "Body",
  "--TypesStyle6FontFamily": "GT-Ultra",
  "--TypesStyle6Max160FontFamily": "GT-Ultra",
  "--TypesStyle6Max160FontWeight": "Regular",
  "--TypesStyle6Max160FontSize": 15,
  "--TypesStyle6Max160LineHeight": 20,
  "--TypesStyle6Max160LineSpacing": 20,
  "--TypesStyle6Max160LetterSpacing": 0,
  "--TypesStyle6Max160iOSClassification": "Body",
  "--TypesStyle6Max135FontFamily": "GT-Ultra",
  "--TypesStyle6Max135FontWeight": "Regular",
  "--TypesStyle6Max135FontSize": 15,
  "--TypesStyle6Max135LineHeight": 20,
  "--TypesStyle6Max135LineSpacing": 20,
  "--TypesStyle6Max135LetterSpacing": 0,
  "--TypesStyle6Max135iOSClassification": "Body",
  "--TypesStyle6Max100FontFamily": "GT-Ultra",
  "--TypesStyle6Max100FontWeight": "Regular",
  "--TypesStyle6Max100FontSize": 15,
  "--TypesStyle6Max100LineHeight": 20,
  "--TypesStyle6Max100LineSpacing": 20,
  "--TypesStyle6Max100LineSpacing2": 20,
  "--TypesStyle6Max100LetterSpacing": 0,
  "--TypesStyle6Max100iOSClassification": "Body",
  "--TypesStyle6FontWeight": "Regular",
  "--TypesStyle6FontSize": 15,
  "--TypesStyle6LineHeight": 20,
  "--TypesStyle6LineSpacing": 20,
  "--TypesStyle6LetterSpacing": 0,
  "--TypesStyle6iOSClassification": "Body",
  "--TypesStyle7FontFamily": "GT-Ultra",
  "--TypesStyle7Max160FontFamily": "GT-Ultra",
  "--TypesStyle7Max160FontWeight": "Bold",
  "--TypesStyle7Max160FontSize": 15,
  "--TypesStyle7Max160LineHeight": 20,
  "--TypesStyle7Max160LineSpacing": 20,
  "--TypesStyle7Max160LetterSpacing": 0,
  "--TypesStyle7Max160iOSClassification": "Body",
  "--TypesStyle7Max135FontFamily": "GT-Ultra",
  "--TypesStyle7Max135FontWeight": "Bold",
  "--TypesStyle7Max135FontSize": 15,
  "--TypesStyle7Max135LineHeight": 20,
  "--TypesStyle7Max135LineSpacing": 20,
  "--TypesStyle7Max135LetterSpacing": 0,
  "--TypesStyle7Max135iOSClassification": "Body",
  "--TypesStyle7Max100FontFamily": "GT-Ultra",
  "--TypesStyle7Max100FontWeight": "Bold",
  "--TypesStyle7Max100FontSize": 15,
  "--TypesStyle7Max100LineHeight": 20,
  "--TypesStyle7Max100LineSpacing": 20,
  "--TypesStyle7Max100LetterSpacing": 0,
  "--TypesStyle7Max100iOSClassification": "Body",
  "--TypesStyle7FontWeight": "Bold",
  "--TypesStyle7FontSize": 15,
  "--TypesStyle7LineHeight": 20,
  "--TypesStyle7LineSpacing": 20,
  "--TypesStyle7LetterSpacing": 0,
  "--TypesStyle7iOSClassification": "Body",
  "--TypesStyle5FontWeight": "Regular",
  "--TypesStyle5FontSize": 17,
  "--TypesStyle5LineHeight": 22,
  "--TypesStyle5LineSpacing": 22,
  "--TypesStyle5LetterSpacing": 0,
  "--TypesStyle5iOSClassification": "Body",
  "--TypesStyle8FontFamily": "GT-Ultra",
  "--TypesStyle8Max160FontFamily": "GT-Ultra",
  "--TypesStyle8Max160FontWeight": "Regular",
  "--TypesStyle8Max160FontSize": 14,
  "--TypesStyle8Max160LineHeight": 20,
  "--TypesStyle8Max160LineSpacing": 20,
  "--TypesStyle8Max160LetterSpacing": 0,
  "--TypesStyle8Max160iOSClassification": "Subheadline",
  "--TypesStyle8Max135FontFamily": "GT-Ultra",
  "--TypesStyle8Max135FontWeight": "Regular",
  "--TypesStyle8Max135FontSize": 14,
  "--TypesStyle8Max135LineHeight": 20,
  "--TypesStyle8Max135LineSpacing": 20,
  "--TypesStyle8Max135LetterSpacing": 0,
  "--TypesStyle8Max135iOSClassification": "Subheadline",
  "--TypesStyle8Max100FontFamily": "GT-Ultra",
  "--TypesStyle8Max100FontWeight": "Regular",
  "--TypesStyle8Max100FontSize": 14,
  "--TypesStyle8Max100LineHeight": 20,
  "--TypesStyle8Max100LineSpacing": 20,
  "--TypesStyle8Max100LetterSpacing": 0,
  "--TypesStyle8Max100iOSClassification": "Subheadline",
  "--TypesStyle8FontWeight": "Regular",
  "--TypesStyle8FontSize": 14,
  "--TypesStyle8LineHeight": 20,
  "--TypesStyle8LineSpacing": 20,
  "--TypesStyle8LetterSpacing": 0,
  "--TypesStyle8iOSClassification": "Subheadline",
  "--TypesStyle9FontFamily": "GT-Ultra",
  "--TypesStyle9Max160FontFamily": "GT-Ultra",
  "--TypesStyle9Max160FontWeight": "Regular",
  "--TypesStyle9Max160FontSize": 12,
  "--TypesStyle9Max160LineHeight": 18,
  "--TypesStyle9Max160LineSpacing": 18,
  "--TypesStyle9Max160LetterSpacing": 0,
  "--TypesStyle9Max160iOSClassification": "Footnote",
  "--TypesStyle9Max135FontFamily": "GT-Ultra",
  "--TypesStyle9Max135FontWeight": "Regular",
  "--TypesStyle9Max135FontSize": 12,
  "--TypesStyle9Max135LineHeight": 18,
  "--TypesStyle9Max135LineSpacing": 18,
  "--TypesStyle9Max135LetterSpacing": 0,
  "--TypesStyle9Max135iOSClassification": "Footnote",
  "--TypesStyle9Max100FontFamily": "GT-Ultra",
  "--TypesStyle9Max100FontWeight": "Regular",
  "--TypesStyle9Max100FontSize": 12,
  "--TypesStyle9Max100LineHeight": 18,
  "--TypesStyle9Max100LineSpacing": 18,
  "--TypesStyle9Max100LetterSpacing": 0,
  "--TypesStyle9Max100iOSClassification": "Footnote",
  "--TypesStyle9FontWeight": "Regular",
  "--TypesStyle9FontSize": 12,
  "--TypesStyle9LineHeight": 18,
  "--TypesStyle9LineSpacing": 18,
  "--TypesStyle9LetterSpacing": 0,
  "--TypesStyle10FontFamily": "GT-Ultra",
  "--TypesStyle9iOSClassification": "Footnote",
  "--TypesStyle10Max160FontFamily": "GT-Ultra",
  "--TypesStyle10Max160FontWeight": "Bold",
  "--TypesStyle10Max160FontSize": 12,
  "--TypesStyle10Max160LineHeight": 18,
  "--TypesStyle10Max160LineSpacing": 18,
  "--TypesStyle10Max160LetterSpacing": 0,
  "--TypesStyle10Max160iOSClassification": "Footnote",
  "--TypesStyle10Max135FontFamily": "GT-Ultra",
  "--TypesStyle10Max135FontWeight": "Bold",
  "--TypesStyle10Max135FontSize": 12,
  "--TypesStyle10Max135LineHeight": 18,
  "--TypesStyle10Max135LineSpacing": 18,
  "--TypesStyle10Max135LetterSpacing": 0,
  "--TypesStyle10Max135iOSClassification": "Footnote",
  "--TypesStyle10Max100FontFamily": "GT-Ultra",
  "--TypesStyle10Max100FontWeight": "Bold",
  "--TypesStyle10Max100FontSize": 12,
  "--TypesStyle10Max100LineHeight": 18,
  "--TypesStyle10Max100LineSpacing": 18,
  "--TypesStyle10Max100LetterSpacing": 0,
  "--TypesStyle10Max100iOSClassification": "Footnote",
  "--TypesStyle11FontFamily": "GT-Ultra",
  "--TypesStyle11Max160FontFamily": "GT-Ultra",
  "--TypesStyle11Max160FontWeight": "Bold",
  "--TypesStyle11Max160FontSize": 14,
  "--TypesStyle11Max160LineHeight": 20,
  "--TypesStyle11Max160LineSpacing": 20,
  "--TypesStyle11Max160LetterSpacing": 0,
  "--TypesStyle11Max160iOSClassification": "Subheadline",
  "--TypesStyle11Max135FontFamily": "GT-Ultra",
  "--TypesStyle11Max135FontWeight": "Bold",
  "--TypesStyle11Max135FontSize": 14,
  "--TypesStyle11Max135LineHeight": 20,
  "--TypesStyle11Max135LineSpacing": 20,
  "--TypesStyle11Max135LetterSpacing": 0,
  "--TypesStyle11Max135iOSClassification": "Subheadline",
  "--TypesStyle11Max100FontFamily": "GT-Ultra",
  "--TypesStyle11Max100FontWeight": "Bold",
  "--TypesStyle11Max100FontSize": 14,
  "--TypesStyle11Max100LineHeight": 20,
  "--TypesStyle11Max100LineSpacing": 20,
  "--TypesStyle11Max100LetterSpacing": 0,
  "--TypesStyle11Max100iOSClassification": "Subheadline",
  "--TypesStyle11FontWeight": "Bold",
  "--TypesStyle11FontSize": 14,
  "--TypesStyle11LineHeight": 20,
  "--TypesStyle11LineSpacing": 20,
  "--TypesStyle11LetterSpacing": 0,
  "--TypesStyle11iOSClassification": "Subheadline",
  "--TypesStyle10FontWeight": "Bold",
  "--TypesStyle10FontSize": 12,
  "--TypesStyle10LineHeight": 18,
  "--TypesStyle10LineSpacing": 18,
  "--TypesStyle10LetterSpacing": 0,
  "--TypesStyle10iOSClassification": "Footnote",
  "--TypesStyle12FontFamily": "GT-Ultra",
  "--TypesStyle12Fontweight": "Bold",
  "--TypesStyle12FontSize": 11,
  "--TypesStyle12LineHeight": 16,
  "--TypesStyle12LineSpacing": 16,
  "--TypesStyle12LetterSpacing": 0,
  "--TypesStyle12iOSClassification": "Caption-1",
  "--TypesStyle12Max160FontFamily": "GT-Ultra",
  "--TypesStyle12Max160Fontweight": "Bold",
  "--TypesStyle12Max160FontSize": 11,
  "--TypesStyle12Max160LineHeight": 16,
  "--TypesStyle12Max160LineSpacing": 16,
  "--TypesStyle12Max160LetterSpacing": 0,
  "--TypesStyle12Max160iOSClassification": "Caption-1",
  "--TypesStyle12Max135FontFamily": "GT-Ultra",
  "--TypesStyle12Max135Fontweight": "Bold",
  "--TypesStyle12Max135FontSize": 11,
  "--TypesStyle12Max135LineHeight": 16,
  "--TypesStyle12Max135LineSpacing": 16,
  "--TypesStyle12Max135LetterSpacing": 0,
  "--TypesStyle12Max135iOSClassification": "Caption-1",
  "--TypesStyle12Max100FontFamily": "GT-Ultra",
  "--TypesStyle12Max100Fontweight": "Bold",
  "--TypesStyle12Max100FontSize": 11,
  "--TypesStyle12Max100LineHeight": 16,
  "--TypesStyle12Max100LineSpacing": 16,
  "--TypesStyle12Max100LetterSpacing": 0,
  "--TypesStyle12Max100iOSClassification": "Caption-1",
  "--TypesStyle13FontFamily": "GT-Ultra",
  "--TypesStyle13Fontweight": "Regular",
  "--TypesStyle13FontSize": 11,
  "--TypesStyle13LineHeight": 16,
  "--TypesStyle13LineSpacing": 16,
  "--TypesStyle13LetterSpacing": 0,
  "--TypesStyle13iOSClassification": "Caption-1",
  "--TypesStyle13Max160FontFamily": "GT-Ultra",
  "--TypesStyle13Max160Fontweight": "Regular",
  "--TypesStyle13Max160FontSize": 11,
  "--TypesStyle13Max160LineHeight": 16,
  "--TypesStyle13Max160LineSpacing": 16,
  "--TypesStyle13Max160LetterSpacing": 0,
  "--TypesStyle13Max160iOSClassification": "Caption-1",
  "--TypesStyle13Max135FontFamily": "GT-Ultra",
  "--TypesStyle13Max135Fontweight": "Regular",
  "--TypesStyle13Max135FontSize": 11,
  "--TypesStyle13Max135LineHeight": 16,
  "--TypesStyle13Max135LineSpacing": 16,
  "--TypesStyle13Max135LetterSpacing": 0,
  "--TypesStyle13Max135iOSClassification": "Caption-1",
  "--TypesStyle13Max100FontFamily": "GT-Ultra",
  "--TypesStyle13Max100Fontweight": "Regular",
  "--TypesStyle13Max100FontSize": 11,
  "--TypesStyle13Max100LineHeight": 16,
  "--TypesStyle13Max100LineSpacing": 16,
  "--TypesStyle13Max100LetterSpacing": 0,
  "--TypesStyle13Max100iOSClassification": "Caption-1",
  "--ComponentTempSpinnerSpinnerType01": 0,
  "--ComponentTempSpinnerSpinnerType02": 0,
  "--ComponentTempWarningViewText": "rgba(230,109,0,1)",
  "--ComponentTempNotificationPillCriticalBackgroundDefault": "rgba(219,15,48,1)",
  "--ComponentTempNotificationPillCriticalTextDefault": "rgba(255,255,255,1)",
  "--LocalDigitalTransactionListItemTextIncoming": "rgba(0,133,93,1)",
  "--LocalDigitalTransactionListItemTextOutgoing": "rgba(0,0,0,1)",
  "--LocalDigitalTransactionMerchantLogoBackground": "rgba(255,255,255,1)",
  "--ComponentSpinnerSplashScreenStyle02GradientStop01": "rgba(0,0,0,0)",
  "--ComponentSpinnerSplashScreenStyle02GradientStop02": "rgba(0,0,0,1)",
  "--ComponentSpinnerSplashScreenStyle02Icon": "rgba(0,0,0,1)",
  "--ComponentSpinnerStyle01": 0,
  "--ComponentSpinnerStyle02": 0,
  "--ComponentSpinnerStyle03": 0,
  "--LocalPaymentsGeneratedImageBackground": "rgba(255,255,255,1)",
  "--ComponentSpinnerModalStyle01Border": "rgba(0,0,0,1)",
  "--ComponentSpinnerModalStyle01BorderHighlight": "rgba(11,226,72,1)",
  "--ComponentSpinnerModalStyle01Icon": "rgba(0,0,0,1)",
  "--ComponentSpinnerModalStyle02GradientStop01": "rgba(0,0,0,0)",
  "--ComponentSpinnerModalStyle02GradientStop02": "rgba(0,0,0,1)",
  "--ComponentSpinnerModalStyle02Icon": "rgba(0,0,0,1)",
  "--ComponentInputRadioButtonDot": "rgba(0,0,0,1)"
}